dj_svg/__init__.py
dj_svg/exceptions.py
dj_svg/tests.py
dj_svg/templatetags/__init__.py
dj_svg/templatetags/svg.py
dj_svg-0.3.1.dist-info/METADATA
dj_svg-0.3.1.dist-info/WHEEL
dj_svg-0.3.1.dist-info/licenses/LICENSE
dj_svg-0.3.1.dist-info/RECORD
